opendataapi/__init__.py
opendataapi/main.py
opendataapi-0.1.3.dist-info/METADATA
opendataapi-0.1.3.dist-info/WHEEL
opendataapi-0.1.3.dist-info/top_level.txt
opendataapi-0.1.3.dist-info/RECORD
