Metadata-Version: 2.1
Name: opendataapi
Version: 0.1.3
Summary: for explain about pypi deploy
Home-page: https://github.com/mskim8717/opendataapi
Author: minsoo.Kim
Author-email: ms.kim8717@gmail.com
License: UNKNOWN
Download-URL: https://github.com/mskim8717/opendataapi/archive/master.zip
Keywords: pypi deploy
Platform: UNKNOWN
Classifier: Programming Language :: Python :: 3
Classifier: Programming Language :: Python :: 3.2
Classifier: Programming Language :: Python :: 3.3
Classifier: Programming Language :: Python :: 3.4
Classifier: Programming Language :: Python :: 3.5
Classifier: Programming Language :: Python :: 3.6
Classifier: Programming Language :: Python :: 3.7
Requires-Python: >=3
